
{
    "data": {
        "request": [
            {
                "type": "City",
                "query": "Singapore, Singapore"
            }
        ],
        "current_condition": [
            {
                "observation_time": "09:08 AM",
                "temp_C": "32",
                "temp_F": "90",
                "weatherCode": "116",
                "weatherIconUrl": [
                    {
                        "value": "http://cdn.worldweatheronline.net/images/wsymbols01_png_64/wsymbol_0002_sunny_intervals.png"
                    }
                ],
                "weatherDesc": [
                    {
                        "value": "Partly cloudy"
                    }
                ],
                "windspeedMiles": "14",
                "windspeedKmph": "22",
                "winddirDegree": "190",
                "winddir16Point": "S",
                "precipMM": "2.5",
                "precipInches": "0.1",
                "humidity": "63",
                "visibility": "10",
                "visibilityMiles": "6",
                "pressure": "1008",
                "pressureInches": "30",
                "cloudcover": "75",
                "FeelsLikeC": "38",
                "FeelsLikeF": "100",
                "uvIndex": 8
            }
        ],
        "weather": [
            {
                "date": "2019-08-05",
                "astronomy": [
                    {
                        "sunrise": "07:06 AM",
                        "sunset": "07:16 PM",
                        "moonrise": "10:49 AM",
                        "moonset": "11:14 PM",
                        "moon_phase": "Waxing Crescent",
                        "moon_illumination": "27"
                    }
                ],
                "maxtempC": "30",
                "maxtempF": "85",
                "mintempC": "28",
                "mintempF": "82",
                "avgtempC": "28",
                "avgtempF": "83",
                "totalSnow_cm": "0.0",
                "sunHour": "8.8",
                "uvIndex": "7",
                "hourly": [
                    {
                        "time": "0",
                        "tempC": "28",
                        "tempF": "83",
                        "windspeedMiles": "12",
                        "windspeedKmph": "20",
                        "winddirDegree": "137",
                        "winddir16Point": "SE",
                        "weatherCode": "116",
                        "weatherIconUrl": [
                            {
                                "value": "http://cdn.worldweatheronline.net/images/wsymbols01_png_64/wsymbol_0004_black_low_cloud.png"
                            }
                        ],
                        "weatherDesc": [
                            {
                                "value": "Partly cloudy"
                            }
                        ],
                        "precipMM": "0.0",
                        "precipInches": "0.0",
                        "humidity": "77",
                        "visibility": "10",
                        "visibilityMiles": "6",
                        "pressure": "1009",
                        "pressureInches": "30",
                        "cloudcover": "19",
                        "HeatIndexC": "32",
                        "HeatIndexF": "90",
                        "DewPointC": "24",
                        "DewPointF": "74",
                        "WindChillC": "28",
                        "WindChillF": "83",
                        "WindGustMiles": "18",
                        "WindGustKmph": "28",
                        "FeelsLikeC": "32",
                        "FeelsLikeF": "90",
                        "chanceofrain": "0",
                        "chanceofremdry": "88",
                        "chanceofwindy": "0",
                        "chanceofovercast": "40",
                        "chanceofsunshine": "79",
                        "chanceoffrost": "0",
                        "chanceofhightemp": "47",
                        "chanceoffog": "0",
                        "chanceofsnow": "0",
                        "chanceofthunder": "0",
                        "uvIndex": "0"
                    },
                    {
                        "time": "300",
                        "tempC": "28",
                        "tempF": "82",
                        "windspeedMiles": "14",
                        "windspeedKmph": "22",
                        "winddirDegree": "139",
                        "winddir16Point": "SE",
                        "weatherCode": "176",
                        "weatherIconUrl": [
                            {
                                "value": "http://cdn.worldweatheronline.net/images/wsymbols01_png_64/wsymbol_0025_light_rain_showers_night.png"
                            }
                        ],
                        "weatherDesc": [
                            {
                                "value": "Patchy rain possible"
                            }
                        ],
                        "precipMM": "0.1",
                        "precipInches": "0.0",
                        "humidity": "79",
                        "visibility": "10",
                        "visibilityMiles": "6",
                        "pressure": "1009",
                        "pressureInches": "30",
                        "cloudcover": "33",
                        "HeatIndexC": "32",
                        "HeatIndexF": "89",
                        "DewPointC": "24",
                        "DewPointF": "75",
                        "WindChillC": "28",
                        "WindChillF": "82",
                        "WindGustMiles": "20",
                        "WindGustKmph": "32",
                        "FeelsLikeC": "32",
                        "FeelsLikeF": "89",
                        "chanceofrain": "25",
                        "chanceofremdry": "53",
                        "chanceofwindy": "0",
                        "chanceofovercast": "56",
                        "chanceofsunshine": "47",
                        "chanceoffrost": "0",
                        "chanceofhightemp": "63",
                        "chanceoffog": "0",
                        "chanceofsnow": "0",
                        "chanceofthunder": "0",
                        "uvIndex": "0"
                    },
                    {
                        "time": "600",
                        "tempC": "28",
                        "tempF": "82",
                        "windspeedMiles": "14",
                        "windspeedKmph": "23",
                        "winddirDegree": "149",
                        "winddir16Point": "SSE",
                        "weatherCode": "116",
                        "weatherIconUrl": [
                            {
                                "value": "http://cdn.worldweatheronline.net/images/wsymbols01_png_64/wsymbol_0004_black_low_cloud.png"
                            }
                        ],
                        "weatherDesc": [
                            {
                                "value": "Partly cloudy"
                            }
                        ],
                        "precipMM": "0.2",
                        "precipInches": "0.0",
                        "humidity": "79",
                        "visibility": "9",
                        "visibilityMiles": "5",
                        "pressure": "1008",
                        "pressureInches": "30",
                        "cloudcover": "53",
                        "HeatIndexC": "32",
                        "HeatIndexF": "89",
                        "DewPointC": "24",
                        "DewPointF": "75",
                        "WindChillC": "28",
                        "WindChillF": "82",
                        "WindGustMiles": "20",
                        "WindGustKmph": "33",
                        "FeelsLikeC": "32",
                        "FeelsLikeF": "89",
                        "chanceofrain": "49",
                        "chanceofremdry": "31",
                        "chanceofwindy": "0",
                        "chanceofovercast": "72",
                        "chanceofsunshine": "26",
                        "chanceoffrost": "0",
                        "chanceofhightemp": "81",
                        "chanceoffog": "0",
                        "chanceofsnow": "0",
                        "chanceofthunder": "0",
                        "uvIndex": "0"
                    },
                    {
                        "time": "900",
                        "tempC": "28",
                        "tempF": "83",
                        "windspeedMiles": "14",
                        "windspeedKmph": "23",
                        "winddirDegree": "161",
                        "winddir16Point": "SSE",
                        "weatherCode": "353",
                        "weatherIconUrl": [
                            {
                                "value": "http://cdn.worldweatheronline.net/images/wsymbols01_png_64/wsymbol_0009_light_rain_showers.png"
                            }
                        ],
                        "weatherDesc": [
                            {
                                "value": "Light rain shower"
                            }
                        ],
                        "precipMM": "0.3",
                        "precipInches": "0.0",
                        "humidity": "77",
                        "visibility": "10",
                        "visibilityMiles": "6",
                        "pressure": "1010",
                        "pressureInches": "30",
                        "cloudcover": "39",
                        "HeatIndexC": "32",
                        "HeatIndexF": "90",
                        "DewPointC": "24",
                        "DewPointF": "75",
                        "WindChillC": "28",
                        "WindChillF": "83",
                        "WindGustMiles": "19",
                        "WindGustKmph": "31",
                        "FeelsLikeC": "32",
                        "FeelsLikeF": "90",
                        "chanceofrain": "26",
                        "chanceofremdry": "62",
                        "chanceofwindy": "0",
                        "chanceofovercast": "50",
                        "chanceofsunshine": "51",
                        "chanceoffrost": "0",
                        "chanceofhightemp": "46",
                        "chanceoffog": "0",
                        "chanceofsnow": "0",
                        "chanceofthunder": "0",
                        "uvIndex": "6"
                    },
                    {
                        "time": "1200",
                        "tempC": "29",
                        "tempF": "84",
                        "windspeedMiles": "15",
                        "windspeedKmph": "24",
                        "winddirDegree": "165",
                        "winddir16Point": "SSE",
                        "weatherCode": "176",
                        "weatherIconUrl": [
                            {
                                "value": "http://cdn.worldweatheronline.net/images/wsymbols01_png_64/wsymbol_0009_light_rain_showers.png"
                            }
                        ],
                        "weatherDesc": [
                            {
                                "value": "Patchy rain possible"
                            }
                        ],
                        "precipMM": "1.4",
                        "precipInches": "0.1",
                        "humidity": "73",
                        "visibility": "10",
                        "visibilityMiles": "6",
                        "pressure": "1010",
                        "pressureInches": "30",
                        "cloudcover": "81",
                        "HeatIndexC": "34",
                        "HeatIndexF": "92",
                        "DewPointC": "24",
                        "DewPointF": "75",
                        "WindChillC": "29",
                        "WindChillF": "84",
                        "WindGustMiles": "21",
                        "WindGustKmph": "34",
                        "FeelsLikeC": "34",
                        "FeelsLikeF": "92",
                        "chanceofrain": "81",
                        "chanceofremdry": "0",
                        "chanceofwindy": "0",
                        "chanceofovercast": "84",
                        "chanceofsunshine": "0",
                        "chanceoffrost": "0",
                        "chanceofhightemp": "48",
                        "chanceoffog": "0",
                        "chanceofsnow": "0",
                        "chanceofthunder": "0",
                        "uvIndex": "6"
                    },
                    {
                        "time": "1500",
                        "tempC": "29",
                        "tempF": "85",
                        "windspeedMiles": "14",
                        "windspeedKmph": "23",
                        "winddirDegree": "170",
                        "winddir16Point": "S",
                        "weatherCode": "176",
                        "weatherIconUrl": [
                            {
                                "value": "http://cdn.worldweatheronline.net/images/wsymbols01_png_64/wsymbol_0009_light_rain_showers.png"
                            }
                        ],
                        "weatherDesc": [
                            {
                                "value": "Patchy rain possible"
                            }
                        ],
                        "precipMM": "2.0",
                        "precipInches": "0.1",
                        "humidity": "71",
                        "visibility": "9",
                        "visibilityMiles": "5",
                        "pressure": "1008",
                        "pressureInches": "30",
                        "cloudcover": "72",
                        "HeatIndexC": "34",
                        "HeatIndexF": "93",
                        "DewPointC": "24",
                        "DewPointF": "74",
                        "WindChillC": "29",
                        "WindChillF": "85",
                        "WindGustMiles": "21",
                        "WindGustKmph": "34",
                        "FeelsLikeC": "34",
                        "FeelsLikeF": "93",
                        "chanceofrain": "82",
                        "chanceofremdry": "0",
                        "chanceofwindy": "0",
                        "chanceofovercast": "92",
                        "chanceofsunshine": "0",
                        "chanceoffrost": "0",
                        "chanceofhightemp": "50",
                        "chanceoffog": "0",
                        "chanceofsnow": "0",
                        "chanceofthunder": "0",
                        "uvIndex": "6"
                    },
                    {
                        "time": "1800",
                        "tempC": "29",
                        "tempF": "84",
                        "windspeedMiles": "12",
                        "windspeedKmph": "20",
                        "winddirDegree": "157",
                        "winddir16Point": "SSE",
                        "weatherCode": "116",
                        "weatherIconUrl": [
                            {
                                "value": "http://cdn.worldweatheronline.net/images/wsymbols01_png_64/wsymbol_0002_sunny_intervals.png"
                            }
                        ],
                        "weatherDesc": [
                            {
                                "value": "Partly cloudy"
                            }
                        ],
                        "precipMM": "0.7",
                        "precipInches": "0.0",
                        "humidity": "73",
                        "visibility": "9",
                        "visibilityMiles": "5",
                        "pressure": "1007",
                        "pressureInches": "30",
                        "cloudcover": "52",
                        "HeatIndexC": "33",
                        "HeatIndexF": "92",
                        "DewPointC": "24",
                        "DewPointF": "74",
                        "WindChillC": "29",
                        "WindChillF": "84",
                        "WindGustMiles": "16",
                        "WindGustKmph": "26",
                        "FeelsLikeC": "33",
                        "FeelsLikeF": "92",
                        "chanceofrain": "51",
                        "chanceofremdry": "29",
                        "chanceofwindy": "0",
                        "chanceofovercast": "76",
                        "chanceofsunshine": "25",
                        "chanceoffrost": "0",
                        "chanceofhightemp": "49",
                        "chanceoffog": "0",
                        "chanceofsnow": "0",
                        "chanceofthunder": "0",
                        "uvIndex": "7"
                    },
                    {
                        "time": "2100",
                        "tempC": "28",
                        "tempF": "83",
                        "windspeedMiles": "12",
                        "windspeedKmph": "19",
                        "winddirDegree": "128",
                        "winddir16Point": "SE",
                        "weatherCode": "116",
                        "weatherIconUrl": [
                            {
                                "value": "http://cdn.worldweatheronline.net/images/wsymbols01_png_64/wsymbol_0004_black_low_cloud.png"
                            }
                        ],
                        "weatherDesc": [
                            {
                                "value": "Partly cloudy"
                            }
                        ],
                        "precipMM": "0.0",
                        "precipInches": "0.0",
                        "humidity": "78",
                        "visibility": "10",
                        "visibilityMiles": "6",
                        "pressure": "1008",
                        "pressureInches": "30",
                        "cloudcover": "7",
                        "HeatIndexC": "32",
                        "HeatIndexF": "90",
                        "DewPointC": "24",
                        "DewPointF": "75",
                        "WindChillC": "28",
                        "WindChillF": "83",
                        "WindGustMiles": "16",
                        "WindGustKmph": "26",
                        "FeelsLikeC": "32",
                        "FeelsLikeF": "90",
                        "chanceofrain": "0",
                        "chanceofremdry": "86",
                        "chanceofwindy": "0",
                        "chanceofovercast": "40",
                        "chanceofsunshine": "77",
                        "chanceoffrost": "0",
                        "chanceofhightemp": "47",
                        "chanceoffog": "0",
                        "chanceofsnow": "0",
                        "chanceofthunder": "0",
                        "uvIndex": "0"
                    }
                ]
            }
        ],
        "ClimateAverages": [
            {
                "month": [
                    {
                        "index": "1",
                        "name": "January",
                        "avgMinTemp": "24.8",
                        "avgMinTemp_F": "76.7",
                        "absMaxTemp": "31.00194",
                        "absMaxTemp_F": "87.8",
                        "avgDailyRainfall": "4.62"
                    },
                    {
                        "index": "2",
                        "name": "February",
                        "avgMinTemp": "24.8",
                        "avgMinTemp_F": "76.6",
                        "absMaxTemp": "31.15357",
                        "absMaxTemp_F": "88.1",
                        "avgDailyRainfall": "2.55"
                    },
                    {
                        "index": "3",
                        "name": "March",
                        "avgMinTemp": "25.3",
                        "avgMinTemp_F": "77.5",
                        "absMaxTemp": "32.2129",
                        "absMaxTemp_F": "90.0",
                        "avgDailyRainfall": "3.82"
                    },
                    {
                        "index": "4",
                        "name": "April",
                        "avgMinTemp": "26.0",
                        "avgMinTemp_F": "78.8",
                        "absMaxTemp": "32.81",
                        "absMaxTemp_F": "91.1",
                        "avgDailyRainfall": "5.00"
                    },
                    {
                        "index": "5",
                        "name": "May",
                        "avgMinTemp": "26.5",
                        "avgMinTemp_F": "79.7",
                        "absMaxTemp": "32.7842",
                        "absMaxTemp_F": "91.0",
                        "avgDailyRainfall": "3.79"
                    },
                    {
                        "index": "6",
                        "name": "June",
                        "avgMinTemp": "26.3",
                        "avgMinTemp_F": "79.4",
                        "absMaxTemp": "32.43697",
                        "absMaxTemp_F": "90.4",
                        "avgDailyRainfall": "3.06"
                    },
                    {
                        "index": "7",
                        "name": "July",
                        "avgMinTemp": "26.1",
                        "avgMinTemp_F": "79.1",
                        "absMaxTemp": "32.18419",
                        "absMaxTemp_F": "89.9",
                        "avgDailyRainfall": "2.18"
                    },
                    {
                        "index": "8",
                        "name": "August",
                        "avgMinTemp": "26.1",
                        "avgMinTemp_F": "79.0",
                        "absMaxTemp": "32.61948",
                        "absMaxTemp_F": "90.7",
                        "avgDailyRainfall": "2.38"
                    },
                    {
                        "index": "9",
                        "name": "September",
                        "avgMinTemp": "25.9",
                        "avgMinTemp_F": "78.6",
                        "absMaxTemp": "32.9179",
                        "absMaxTemp_F": "91.3",
                        "avgDailyRainfall": "2.36"
                    },
                    {
                        "index": "10",
                        "name": "October",
                        "avgMinTemp": "26.0",
                        "avgMinTemp_F": "78.8",
                        "absMaxTemp": "33.09821",
                        "absMaxTemp_F": "91.6",
                        "avgDailyRainfall": "3.99"
                    },
                    {
                        "index": "11",
                        "name": "November",
                        "avgMinTemp": "25.7",
                        "avgMinTemp_F": "78.2",
                        "absMaxTemp": "32.2203",
                        "absMaxTemp_F": "90.0",
                        "avgDailyRainfall": "6.16"
                    },
                    {
                        "index": "12",
                        "name": "December",
                        "avgMinTemp": "25.2",
                        "avgMinTemp_F": "77.4",
                        "absMaxTemp": "31.0129",
                        "absMaxTemp_F": "87.8",
                        "avgDailyRainfall": "7.05"
                    }
                ]
            }
        ]
    }
}
